{
  "text": "Guidance for coordination of international arms transfers (a) In general Not later than 180 days after the date of the enactment of this Act, the Secretary of Defense shall issue updated guidance, in accordance with section 382 of title 10, United States Code, to streamline and align the roles, responsibilities, and authorities, and improve transparency, relating to Department of Defense processes for international arms transfers, including foreign military sales. (b) Elements The updated guidance required by subsection (a) shall do the following: (1) Streamline the roles and responsibilities relating to Department processes for international arms transfers (including the foreign military sales and technology security and foreign disclosure processes in accordance with section 1086) so as to ensure effective implementation of such roles and responsibilities among the Under Secretary of Defense for Policy, the Under Secretary of Defense for Acquisition and Sustainment, the Defense Security Cooperation Agency, the Defense Technology Security Administration, and the military departments. (2) Designate a lead official who, in coordination with the Chief Digital and Artificial Intelligence Officer of the Department of Defense, shall be responsible for collecting, tracking, coordinating, and sharing data and information on Foreign Military Sales cases for the purposes of - (A) facilitating transparency across the Department of Defense international cooperation enterprise (including industry and international partners within such enterprise and components and subcomponents of the Department); and (B) sharing information on foreign military sales case development, execution, contracting, and implementation processes. (3) Develop a framework to facilitate the use of the foreign military sales process to deliver defense articles and services to allies and partners through programs other than a program of record in accordance with section 1214 . (4) Set forth foreign military sales-specific guidance that - (A) identifies security cooperation priorities; (B) is informed by priorities identified in the National Defense Strategy, Department planning guidance, and theater campaign plans; and (C) takes into consideration - (i) the risk factors for arms transfers identified in the Arms Export Control Act ( 22 U.S.C. 2751 et seq. ); and (ii) the industrial capacity for production. (c) Briefing Not later than 30 days prior to the issuance of the updated guidance required by subsection (a), the Secretary shall provide the Committee on Armed Services and the Committee on Foreign Relations of the Senate and the Committee on Armed Services and the Committee on Foreign Affairs of the House of Representatives with a briefing on the development and implementation of such guidance that describes the manner in which the procedures set forth in the guidance will streamline, and enhance the transparency of, international cooperation processes of the Department. (d) Dissemination of FMS-specific guidance Not later than 180 days after the date of the enactment of this Act, the Secretary shall disseminate the foreign miliary sales-specific guidance described in subsection (b)(4) to the Department of Defense international cooperation enterprise.",
  "version": "3.2",
  "headline": "Fully Human Written",
  "prediction": "We believe that this document is fully human-written",
  "prediction_short": "Human",
  "fraction_ai": 0.0,
  "fraction_ai_assisted": 0.0,
  "fraction_human": 1.0,
  "num_ai_segments": 0,
  "num_ai_assisted_segments": 0,
  "num_human_segments": 2,
  "windows": [
    {
      "text": "Guidance for coordination of international arms transfers (a) In general Not later than 180 days after the date of the enactment of this Act, the Secretary of Defense shall issue updated guidance, in accordance with section 382 of title 10, United States Code, to streamline and align the roles, responsibilities, and authorities, and improve transparency, relating to Department of Defense processes for international arms transfers, including foreign military sales. (b) Elements The updated guidance required by subsection (a) shall do the following: (1) Streamline the roles and responsibilities relating to Department processes for international arms transfers (including the foreign military sales and technology security and foreign disclosure processes in accordance with section 1086) so as to ensure effective implementation of such roles and responsibilities among the Under Secretary of Defense for Policy, the Under Secretary of Defense for Acquisition and Sustainment, the Defense Security Cooperation Agency, the Defense Technology Security Administration, and the military departments. (2) Designate a lead official who, in coordination with the Chief Digital and Artificial Intelligence Officer of the Department of Defense, shall be responsible for collecting, tracking, coordinating, and sharing data and information on Foreign Military Sales cases for the purposes of - (A) facilitating transparency across the Department of Defense international cooperation enterprise (including industry and international partners within such enterprise and components and subcomponents of the Department); and (B) sharing information on foreign military sales case development, execution, contracting, and implementation processes. (3) Develop a framework to facilitate the use of the foreign military sales process to deliver defense articles and services to allies and partners through programs other than a program of record in accordance with section 1214 . (4) Set forth foreign military sales-specific guidance that - (A) identifies security cooperation priorities; (B) is informed by priorities identified in the National Defense Strategy, Department planning guidance, and theater campaign plans; and (C) takes into consideration - (i) the risk factors for arms transfers identified in the Arms Export Control Act ( 22 U.S.C. 2751 et seq. ); and (ii) the industrial capacity for production. (",
      "label": "Human Written",
      "ai_assistance_score": 0.00491383046998332,
      "confidence": "High",
      "start_index": 0,
      "end_index": 2407,
      "word_count": 344,
      "token_length": 441
    },
    {
      "text": "c) Briefing Not later than 30 days prior to the issuance of the updated guidance required by subsection (a), the Secretary shall provide the Committee on Armed Services and the Committee on Foreign Relations of the Senate and the Committee on Armed Services and the Committee on Foreign Affairs of the House of Representatives with a briefing on the development and implementation of such guidance that describes the manner in which the procedures set forth in the guidance will streamline, and enhance the transparency of, international cooperation processes of the Department. (d) Dissemination of FMS-specific guidance Not later than 180 days after the date of the enactment of this Act, the Secretary shall disseminate the foreign miliary sales-specific guidance described in subsection (b)(4) to the Department of Defense international cooperation enterprise.",
      "label": "Human Written",
      "ai_assistance_score": 0.004997558076865971,
      "confidence": "High",
      "start_index": 2407,
      "end_index": 3271,
      "word_count": 131,
      "token_length": 161
    }
  ],
  "_submission_type": "solo"
}