{
  "text": "Designation of department of defense strategic arctic ports. (a) Sense of Congress . It is the sense of Congress that - (1) the Arctic is a region of strategic importance to the national security interests of the United States and the Department of Defense must better align its presence, force posture, and capabilities to meet the growing array of challenges in the region; and \n (2) although much progress has been made to increase awareness of Arctic issues and to promote increased presence in the region, additional measures, including the designation of one or more strategic Arctic ports, are needed to show the commitment of the United States to this emerging strategic choke point of future great power competition. \n \n (b) Report Required . (1) Consultation. In general . Not later than 180 days after the date of the enactment of this Act, the Secretary of Defense, in consultation with the Chairman of the Joint Chiefs of Staff, the Commanding General of the United States Army Corps of Engineers, the Commandant of the Coast Guard, and the \nAdministrator of the Maritime Administration, shall submit to the congressional defense committees a report evaluating potential sites for one or more strategic ports in the Arctic. \n (2) Elements . Consistent with the updated military strategy for the protection of United States national security interests in the Arctic region set forth in the report required under section 1071 of the National Defense Authorization Act for Fiscal Year 2019 ( Public Law 114\u201392 ; 129 Stat. 992 ), the report required under paragraph (1) shall include - (A) Evaluation. an evaluation of the amount of sufficient and suitable space needed to create capacity for port and other necessary infrastructure for at least one of each of type of Navy or Coast Guard vessel, including an Arleigh Burke class destroyer of the Navy, a national security cutter, and a heavy polar ice breaker of the Coast Guard; \n (B) Evaluation. an evaluation of the amount of sufficient and suitable space needed to create capacity for equipment and fuel storage, technological infrastructure, and civil infrastructure to support military and civilian operations, including - (i) aerospace warning; \n (ii) maritime surface and subsurface warning; \n (iii) maritime control and defense; \n (iv) maritime domain awareness; \n (v) homeland defense; \n (vi) defense support to civil authorities; \n (vii) humanitarian relief; \n (viii) search and rescue; \n (ix) disaster relief; \n (x) oil spill response; \n (xi) medical stabilization and evacuation; and \n (xii) meteorological measurements and forecasting; \n \n (C) an identification of proximity and road access required to an airport designated as a commercial service airport by the Federal Aviation Administration that is capable of supporting military and civilian aircraft for operations designated in subparagraph (B); \n (D) a description of the requirements, to include infrastructure and installations, communications, and logistics necessary to improve response effectiveness to support military and civilian operations described in subparagraph (B); \n (E) an identification of the sites that the Secretary recommends as potential sites for designation as Department of Defense Strategic Arctic Ports; \n (F) Cost estimate. the estimated cost of sufficient construction necessary to initiate and sustain expected operations at such sites; and \n (G) such other information as the Secretary deems relevant. \n \n \n (c) Designation of Strategic Arctic Ports . Deadline. Consultation. Not later than 90 days after the date on which the report required under subsection (b) is submitted, the Secretary of Defense, in consultation with the Chairman of the Joint Chiefs of Staff, the Commanding General of the United States Army Corps of Engineers, the Commandant of the Coast Guard, and the Administrator of the Maritime Administration, may designate one or more ports as Department of Defense \nStrategic Arctic Ports from the sites identified under subsection (b)(2)(E). \n (d) Rule of Construction . Nothing in this section may be construed to authorize any additional appropriations for the Department of Defense for the establishment of any port designated pursuant to this section. \n (e) Arctic Defined . In this section, the term \u201c Arctic \u201d has the meaning given that term in section 112 of the Arctic Research and Policy Act of 1984 ( 15 U.S.C. 4111 ).",
  "version": "3.2",
  "headline": "Fully Human Written",
  "prediction": "We believe that this document is fully human-written",
  "prediction_short": "Human",
  "fraction_ai": 0.0,
  "fraction_ai_assisted": 0.0,
  "fraction_human": 1.0,
  "num_ai_segments": 0,
  "num_ai_assisted_segments": 0,
  "num_human_segments": 2,
  "windows": [
    {
      "text": "Designation of department of defense strategic arctic ports. (a) Sense of Congress . It is the sense of Congress that - (1) the Arctic is a region of strategic importance to the national security interests of the United States and the Department of Defense must better align its presence, force posture, and capabilities to meet the growing array of challenges in the region; and \n (2) although much progress has been made to increase awareness of Arctic issues and to promote increased presence in the region, additional measures, including the designation of one or more strategic Arctic ports, are needed to show the commitment of the United States to this emerging strategic choke point of future great power competition. \n \n (b) Report Required . (1) Consultation. In general . Not later than 180 days after the date of the enactment of this Act, the Secretary of Defense, in consultation with the Chairman of the Joint Chiefs of Staff, the Commanding General of the United States Army Corps of Engineers, the Commandant of the Coast Guard, and the \nAdministrator of the Maritime Administration, shall submit to the congressional defense committees a report evaluating potential sites for one or more strategic ports in the Arctic. \n (2) Elements . Consistent with the updated military strategy for the protection of United States national security interests in the Arctic region set forth in the report required under section 1071 of the National Defense Authorization Act for Fiscal Year 2019 ( Public Law 114\u201392 ; 129 Stat. 992 ), the report required under paragraph (1) shall include - (A) Evaluation. an evaluation of the amount of sufficient and suitable space needed to create capacity for port and other necessary infrastructure for at least one of each of type of Navy or Coast Guard vessel, including an Arleigh Burke class destroyer of the Navy, a national security cutter, and a heavy polar ice breaker of the Coast Guard; \n (B) Evaluation. an evaluation of the amount of sufficient and suitable space needed to create capacity for equipment and fuel storage, technological infrastructure, and civil infrastructure to support military and civilian operations, including - (i) aerospace warning; \n (ii) maritime surface and subsurface warning; \n (iii) maritime control and",
      "label": "Human Written",
      "ai_assistance_score": 0.005083260349541281,
      "confidence": "High",
      "start_index": 0,
      "end_index": 2288,
      "word_count": 366,
      "token_length": 467
    },
    {
      "text": " defense; \n (iv) maritime domain awareness; \n (v) homeland defense; \n (vi) defense support to civil authorities; \n (vii) humanitarian relief; \n (viii) search and rescue; \n (ix) disaster relief; \n (x) oil spill response; \n (xi) medical stabilization and evacuation; and \n (xii) meteorological measurements and forecasting; \n \n (C) an identification of proximity and road access required to an airport designated as a commercial service airport by the Federal Aviation Administration that is capable of supporting military and civilian aircraft for operations designated in subparagraph (B); \n (D) a description of the requirements, to include infrastructure and installations, communications, and logistics necessary to improve response effectiveness to support military and civilian operations described in subparagraph (B); \n (E) an identification of the sites that the Secretary recommends as potential sites for designation as Department of Defense Strategic Arctic Ports; \n (F) Cost estimate. the estimated cost of sufficient construction necessary to initiate and sustain expected operations at such sites; and \n (G) such other information as the Secretary deems relevant. \n \n \n (c) Designation of Strategic Arctic Ports . Deadline. Consultation. Not later than 90 days after the date on which the report required under subsection (b) is submitted, the Secretary of Defense, in consultation with the Chairman of the Joint Chiefs of Staff, the Commanding General of the United States Army Corps of Engineers, the Commandant of the Coast Guard, and the Administrator of the Maritime Administration, may designate one or more ports as Department of Defense \nStrategic Arctic Ports from the sites identified under subsection (b)(2)(E). \n (d) Rule of Construction . Nothing in this section may be construed to authorize any additional appropriations for the Department of Defense for the establishment of any port designated pursuant to this section. \n (e) Arctic Defined . In this section, the term \u201c Arctic \u201d has the meaning given that term in section 112 of the Arctic Research and Policy Act of 1984 ( 15 U.S.C. 4111 ).",
      "label": "Human Written",
      "ai_assistance_score": 0.005349729072164607,
      "confidence": "High",
      "start_index": 2288,
      "end_index": 4411,
      "word_count": 311,
      "token_length": 464
    }
  ],
  "_submission_type": "solo"
}