{
  "text": "Modification of authority to make payments to lessors of privatized military housing. (a) Modification of Payment Authority . Subsection (a) of section 606 of the John S. McCain National Defense Authorization Act for Fiscal Year 2019 ( Public Law 115\u2013232 ; 132 Stat. 1795 ; 10 U.S.C. 2871 note ) is amended to read as follows: \u201c(a) Use of Funds in Connection With MHPI . \u201c(1) Payments to lessors generally . \u201c(A) Effective date. Payment authority . Each month beginning with the first month after the date of the enactment of the National Defense Authorization Act for Fiscal Year 2020, each Secretary of a military department shall use funds, in an amount determined under subparagraph (B), to make payments to lessors of covered housing in the manner provided by this subsection, as in effect on the day before the date of the enactment of the National Defense Authorization Act for Fiscal Year 2020. \n \u201c(B) Determination. Calculation of monthly payments . For purposes of making payments under subparagraph (A) for a month, the Secretary of the military department concerned shall determine the amount equal to 2.5 percent of the aggregate of the amounts calculated under section 403(b)(3)(A)(i) of title 37, United States Code , for covered housing under the jurisdiction of the Secretary for that month. \n \n \u201c(2) Additional payments to lessors responsible for underfunded projects . \u201c(A) Effective date. Payment authority . Each month beginning with the first month after the date of the enactment of the National Defense Authorization Act for Fiscal Year 2020, each Secretary of a military department shall use funds, in an amount determined under subparagraph (B), to make additional payments to certain lessors responsible for underfunded MHPI housing projects identified pursuant to subparagraph (C) for the purposes of future sustainment, recapitalization, and financial sustainability of the projects. \n \u201c(B) Determination. Calculation of monthly payments . For purposes of making payments under subparagraph (A) for a month, the Secretary of the military department concerned shall determine the amount equal to 2.5 percent of the aggregate of the amounts calculated under section 403(b)(3)(A)(i) of title 37, United States Code , for covered housing under the jurisdiction of the Secretary for that month. \n \u201c(C) Assessment. Identification of underfunded projects . The Chief Housing Officer of the Department of Defense, in conjunction with the Secretaries of the military departments, shall assess MHPI housing projects for the purpose of identifying all MHPI housing projects that are underfunded. Once identified, the Chief Housing Officer shall prioritize for payments under subparagraph (A) those MHPI housing projects most in need of funding to rectify such underfunding. \n \n \u201c(3) Alternative authority in event of lack of underfunded projects . \u201c(A) Determination. Consultation. In general . Subject to subparagraph (B), if the Chief Housing Officer determines that no MHPI housing projects for a military department require additional funding under paragraph (2) for a month, the Secretary of the military department concerned, in consultation with the Chief Housing Officer, may allocate the funds otherwise available to the Secretary under such paragraph for that month to support improvements designed to enhance the quality of life of members of the uniformed services and their families who reside in MHPI housing. \n \u201c(B) Certification. Conditions . Before the Secretary of a military department may allocate funds as authorized by subparagraph (A), the Chief Housing Officer shall certify to the Committees on Armed Services of the Senate and the House of Representatives that there are no MHPI housing projects for the military department require additional funding under paragraph (2). The certification shall include sufficient details to show why no projects are determined to need the additional funds. \n \n \u201c(4) Deadline. Briefing required . Not later than March 1, 2020, and each year thereafter, the Secretary of Defense shall provide a briefing to the Committee on Armed Services of the Senate and the House of Representatives detailing the expenditure of funds under paragraphs (2) and (3), the MHPI housing projects receiving funds under such paragraphs, and any other information the Secretary considers relevant.\u201d \n \n . \n (b) 10 USC 2871 note . Effective Date . The amendment made by this section shall take effect on the date of the enactment of this Act and shall apply with respect to months beginning after that date.",
  "version": "3.2",
  "headline": "Fully Human Written",
  "prediction": "We believe that this document is fully human-written",
  "prediction_short": "Human",
  "fraction_ai": 0.0,
  "fraction_ai_assisted": 0.0,
  "fraction_human": 1.0,
  "num_ai_segments": 0,
  "num_ai_assisted_segments": 0,
  "num_human_segments": 3,
  "windows": [
    {
      "text": "Modification of authority to make payments to lessors of privatized military housing. (a) Modification of Payment Authority . Subsection (a) of section 606 of the John S. McCain National Defense Authorization Act for Fiscal Year 2019 ( Public Law 115\u2013232 ; 132 Stat. 1795 ; 10 U.S.C. 2871 note ) is amended to read as follows: \u201c(a) Use of Funds in Connection With MHPI . \u201c(1) Payments to lessors generally . \u201c(A) Effective date. Payment authority . Each month beginning with the first month after the date of the enactment of the National Defense Authorization Act for Fiscal Year 2020, each Secretary of a military department shall use funds, in an amount determined under subparagraph (B), to make payments to lessors of covered housing in the manner provided by this subsection, as in effect on the day before the date of the enactment of the National Defense Authorization Act for Fiscal Year 2020. \n \u201c(B) Determination. Calculation of monthly payments . For purposes of making payments under subparagraph (A) for a month, the Secretary of the military department concerned shall determine the amount equal to 2.5 percent of the aggregate of the amounts calculated under section 403(b)(3)(A)(i) of title 37, United States Code , for covered housing under the jurisdiction of the Secretary for that month. \n \n \u201c(2) Additional payments to lessors responsible for underfunded projects . \u201c(A) Effective date. Payment authority . Each month beginning with the first month after the date of the enactment of the National Defense Authorization Act for Fiscal Year 2020, each Secretary of a military department shall use funds, in an amount determined under subparagraph (B), to make additional payments to certain lessors responsible for underfunded MHPI housing projects identified pursuant to subparagraph (C) for the purposes of future sustainment, recapitalization, and financial sustainability of the projects. \n \u201c(B) Determination. Calculation of monthly payments .",
      "label": "Human Written",
      "ai_assistance_score": 0.006389634194783866,
      "confidence": "High",
      "start_index": 0,
      "end_index": 1968,
      "word_count": 308,
      "token_length": 459
    },
    {
      "text": " For purposes of making payments under subparagraph (A) for a month, the Secretary of the military department concerned shall determine the amount equal to 2.5 percent of the aggregate of the amounts calculated under section 403(b)(3)(A)(i) of title 37, United States Code , for covered housing under the jurisdiction of the Secretary for that month. \n \u201c(C) Assessment. Identification of underfunded projects . The Chief Housing Officer of the Department of Defense, in conjunction with the Secretaries of the military departments, shall assess MHPI housing projects for the purpose of identifying all MHPI housing projects that are underfunded. Once identified, the Chief Housing Officer shall prioritize for payments under subparagraph (A) those MHPI housing projects most in need of funding to rectify such underfunding. \n \n \u201c(3) Alternative authority in event of lack of underfunded projects . \u201c(A) Determination. Consultation. In general . Subject to subparagraph (B), if the Chief Housing Officer determines that no MHPI housing projects for a military department require additional funding under paragraph (2) for a month, the Secretary of the military department concerned, in consultation with the Chief Housing Officer, may allocate the funds otherwise available to the Secretary under such paragraph for that month to support improvements designed to enhance the quality of life of members of the uniformed services and their families who reside in MHPI housing. \n \u201c(B) Certification. Conditions . Before the Secretary of a military department may allocate funds as authorized by subparagraph (A), the Chief Housing Officer shall certify to the Committees on Armed Services of the Senate and the House of Representatives that there are no MHPI housing projects for the military department require additional funding under paragraph (2). The certification shall include sufficient details to show why no projects are determined to need the additional funds. \n \n \u201c(4) Deadline. Briefing required . Not later than March 1, 2020, and each year thereafter, the Secretary of Defense shall provide a briefing to the Committee on Armed Services of the Senate and the House of Representatives detailing the expenditure of funds under paragraphs (2) and (3), the MHPI housing projects receiving funds under such paragraphs, and any other information the Secretary considers relevant.\u201d \n \n . \n (b) 10 USC 2871 note .",
      "label": "Human Written",
      "ai_assistance_score": 0.005884049815507844,
      "confidence": "High",
      "start_index": 1968,
      "end_index": 4384,
      "word_count": 366,
      "token_length": 496
    },
    {
      "text": " Effective Date . The amendment made by this section shall take effect on the date of the enactment of this Act and shall apply with respect to months beginning after that date.",
      "label": "Human Written",
      "ai_assistance_score": 0.005431809928268194,
      "confidence": "High",
      "start_index": 4384,
      "end_index": 4561,
      "word_count": 32,
      "token_length": 34
    }
  ],
  "_submission_type": "solo"
}