{
  "text": "\u201c\u00a7\u202f53201. 46 USC 53201 . Definitions \u201cIn this chapter: \u201c(1) Cable services . The term \u2018 cable services \u2019 means the installation, maintenance, or repair of submarine cables and related equipment, and related cable vessel operations. \n \u201c(2) Cable vessel . The term \u2018 cable vessel \u2019 means a vessel - \u201c(A) classed as a cable ship or cable vessel by, and designed in accordance with the rules of, the American Bureau of Shipping, or another classification society accepted by the Secretary; and \n \u201c(B) capable of installing, maintaining, and repairing submarine cables. \n \n \u201c(3) Cable fleet . The term \u2018 Cable Fleet \u2019 means the Cable Security Fleet established under section 53202(a). \n \u201c(4) Contingency agreement . The term \u2018 Contingency Agreement \u2019 means the agreement required by section 53207. \n \u201c(5) Contractor . The term \u2018 Contractor \u2019 means an owner or operator of a vessel that enters into an Operating Agreement for a cable vessel with the Secretary under section 53203. \n \u201c(6) Fiscal year . The term \u2018 fiscal year \u2019 means any annual period beginning on October 1 and ending on September 30. \n \u201c(7) Operating agency . The term \u2018 Operating Agency \u2019 means that agency or component of the Department of Defense so designated by the Secretary of Defense under this chapter. \n \u201c(8) Operating agreement or agreement . The terms \u2018Operating Agreement\u2019 or \u2018Agreement\u2019 mean the agreement required by section 53203. \n \u201c(9) Person . The term \u2018 person \u2019 includes corporations, partnerships, and associations existing under or authorized by the laws of the United States, or any State, Territory, District, or possession thereof, or of any foreign country. \n \u201c(10) Secretary . The term \u2018 Secretary \u2019 means the Secretary of Transportation. \n \u201c(11) United states . The term \u2018 United States \u2019 includes the States, the District of Columbia, the Commonwealth of Puerto Rico, the Northern Mariana Islands, Guam, American Samoa, and the Virgin Islands. \n \u201c(12) United states citizen trust . \u201c(A) Subject to paragraph (C), the term \u2018 United States citizen trust \u2019 means a trust that is qualified under this paragraph. \n \u201c(B) A trust is qualified under this paragraph with respect to a vessel only if - \u201c(i) it was created under the laws of a state of the United States; \n \u201c(ii) each of the trustees is a citizen of the United States; and \n \u201c(iii) the application for documentation of the vessel under chapter 121 of this title includes the affidavit of each trustee stating that the trustee is not aware of any reason involving a beneficiary of the trust that is not a citizen of the United States, or involving any other person that is not a citizen of the United States, as a result of which the beneficiary or other person would hold more than 25 percent of the aggregate power to influence, or limit the exercise of the authority of, the trustee with respect to matters involving any ownership or operation of the vessel that may adversely affect the interests of the United States. \n \n \u201c(C) If any person that is not a citizen of the United States has authority to direct, or participate in directing, the trustee for a trust in matters involving any ownership or operation of the vessel that may adversely affect the interests of the United States or in removing a trustee for a trust without cause, either directly or indirectly through the control of another person, the trust is not qualified under this paragraph unless the trust instrument provides that persons who are not citizens of the United States may not hold more than 25 percent of the aggregate authority to direct or remove a trustee. \n \u201c(D) This paragraph shall not be considered to prohibit a person who is not a citizen of the United States from holding more than 25 percent of the beneficial interest in a trust.",
  "version": "3.2",
  "headline": "Fully Human Written",
  "prediction": "We believe that this document is fully human-written",
  "prediction_short": "Human",
  "fraction_ai": 0.0,
  "fraction_ai_assisted": 0.0,
  "fraction_human": 1.0,
  "num_ai_segments": 0,
  "num_ai_assisted_segments": 0,
  "num_human_segments": 2,
  "windows": [
    {
      "text": "\u201c\u00a7\u202f53201. 46 USC 53201 . Definitions \u201cIn this chapter: \u201c(1) Cable services . The term \u2018 cable services \u2019 means the installation, maintenance, or repair of submarine cables and related equipment, and related cable vessel operations. \n \u201c(2) Cable vessel . The term \u2018 cable vessel \u2019 means a vessel - \u201c(A) classed as a cable ship or cable vessel by, and designed in accordance with the rules of, the American Bureau of Shipping, or another classification society accepted by the Secretary; and \n \u201c(B) capable of installing, maintaining, and repairing submarine cables. \n \n \u201c(3) Cable fleet . The term \u2018 Cable Fleet \u2019 means the Cable Security Fleet established under section 53202(a). \n \u201c(4) Contingency agreement . The term \u2018 Contingency Agreement \u2019 means the agreement required by section 53207. \n \u201c(5) Contractor . The term \u2018 Contractor \u2019 means an owner or operator of a vessel that enters into an Operating Agreement for a cable vessel with the Secretary under section 53203. \n \u201c(6) Fiscal year . The term \u2018 fiscal year \u2019 means any annual period beginning on October 1 and ending on September 30. \n \u201c(7) Operating agency . The term \u2018 Operating Agency \u2019 means that agency or component of the Department of Defense so designated by the Secretary of Defense under this chapter. \n \u201c(8) Operating agreement or agreement . The terms \u2018Operating Agreement\u2019 or \u2018Agreement\u2019 mean the agreement required by section 53203. \n \u201c(9) Person . The term \u2018 person \u2019 includes corporations, partnerships, and associations existing under or authorized by the laws of the United States, or any State, Territory, District, or possession thereof, or of any foreign country. \n \u201c(10) Secretary . The term \u2018 Secretary \u2019 means the Secretary of Transportation. \n \u201c(11) United states . The term \u2018 United States \u2019 includes the States, the District of Columbia, the Commonwealth of Puerto Rico, the Northern Mariana Islands, Guam, American Samoa, and the Virgin Islands. \n \u201c(12) United states citizen trust . \u201c(",
      "label": "Human Written",
      "ai_assistance_score": 0.008017247232298056,
      "confidence": "High",
      "start_index": 0,
      "end_index": 1976,
      "word_count": 322,
      "token_length": 481
    },
    {
      "text": "A) Subject to paragraph (C), the term \u2018 United States citizen trust \u2019 means a trust that is qualified under this paragraph. \n \u201c(B) A trust is qualified under this paragraph with respect to a vessel only if - \u201c(i) it was created under the laws of a state of the United States; \n \u201c(ii) each of the trustees is a citizen of the United States; and \n \u201c(iii) the application for documentation of the vessel under chapter 121 of this title includes the affidavit of each trustee stating that the trustee is not aware of any reason involving a beneficiary of the trust that is not a citizen of the United States, or involving any other person that is not a citizen of the United States, as a result of which the beneficiary or other person would hold more than 25 percent of the aggregate power to influence, or limit the exercise of the authority of, the trustee with respect to matters involving any ownership or operation of the vessel that may adversely affect the interests of the United States. \n \n \u201c(C) If any person that is not a citizen of the United States has authority to direct, or participate in directing, the trustee for a trust in matters involving any ownership or operation of the vessel that may adversely affect the interests of the United States or in removing a trustee for a trust without cause, either directly or indirectly through the control of another person, the trust is not qualified under this paragraph unless the trust instrument provides that persons who are not citizens of the United States may not hold more than 25 percent of the aggregate authority to direct or remove a trustee. \n \u201c(D) This paragraph shall not be considered to prohibit a person who is not a citizen of the United States from holding more than 25 percent of the beneficial interest in a trust.",
      "label": "Human Written",
      "ai_assistance_score": 0.005842165959378083,
      "confidence": "High",
      "start_index": 1976,
      "end_index": 3770,
      "word_count": 317,
      "token_length": 382
    }
  ],
  "_submission_type": "solo"
}